genicam2-0.0.0.dev5472.data/purelib/genicam2/README.rst
genicam2-0.0.0.dev5472.data/purelib/genicam2/TLSimu.cti
genicam2-0.0.0.dev5472.data/purelib/genicam2/__init__.py
genicam2-0.0.0.dev5472.data/purelib/genicam2/_genapi.so
genicam2-0.0.0.dev5472.data/purelib/genicam2/_gentl.so
genicam2-0.0.0.dev5472.data/purelib/genicam2/genapi.py
genicam2-0.0.0.dev5472.data/purelib/genicam2/gentl.py
genicam2-0.0.0.dev5472.data/purelib/genicam2/libGCBase_clang100_v3_1_kznr_5472.dylib
genicam2-0.0.0.dev5472.data/purelib/genicam2/libGenApi_clang100_v3_1_kznr_5472.dylib
genicam2-0.0.0.dev5472.data/purelib/genicam2/libLog_clang100_v3_1_kznr_5472.dylib
genicam2-0.0.0.dev5472.data/purelib/genicam2/libMathParser_clang100_v3_1_kznr_5472.dylib
genicam2-0.0.0.dev5472.data/purelib/genicam2/libNodeMapData_clang100_v3_1_kznr_5472.dylib
genicam2-0.0.0.dev5472.data/purelib/genicam2/libVirtualFG.dylib
genicam2-0.0.0.dev5472.data/purelib/genicam2/libXmlParser_clang100_v3_1_kznr_5472.dylib
genicam2-0.0.0.dev5472.data/purelib/genicam2/licenses/GenICam_License_20180629.pdf
genicam2-0.0.0.dev5472.data/purelib/genicam2/licenses/xxhash_License.txt
genicam2-0.0.0.dev5472.dist-info/LICENSE.txt
genicam2-0.0.0.dev5472.dist-info/METADATA
genicam2-0.0.0.dev5472.dist-info/RECORD
genicam2-0.0.0.dev5472.dist-info/WHEEL
genicam2-0.0.0.dev5472.dist-info/top_level.txt
