Metadata-Version: 2.0
Name: genicam2
Version: 0.0.0.dev5472
Summary: The official Python Binding for the GenICam GenApi & the GenTL Producers
Home-page: https://www.emva.org
Author: The GenICam Committee
Author-email: genicam@list.stemmer-imaging.com
License: The GenICam License Version 1.6
Download-URL: https://pypi.org/project/genicam2/
Platform: UNKNOWN
Classifier: Development Status :: 3 - Alpha
Classifier: Intended Audience :: Science/Research
Classifier: Intended Audience :: Education
Classifier: Intended Audience :: Developers
Classifier: License :: Other/Proprietary License
Classifier: Operating System :: MacOS :: MacOS X
Classifier: Operating System :: Microsoft :: Windows
Classifier: Operating System :: POSIX
Classifier: Programming Language :: Python :: 3
Provides: genicam2
